seminario/__init__.py
seminario/config/__init__.py
seminario/config/config.py
seminario/config/default.yml
seminario/poster.py
seminario/seminar.py
seminario/utils/__init__.py
seminario/utils/bunch.py
seminario/utils/table.py
seminario-0.3.0.dist-info/LICENSE
seminario-0.3.0.dist-info/WHEEL
seminario-0.3.0.dist-info/METADATA
seminario-0.3.0.dist-info/RECORD
