Metadata-Version: 2.1
Name: seminario
Version: 0.3.0
Summary: Python package for seminar organization.
License: BSD-3-Clause
Author: Shota Imaki
Author-email: shota.imaki@icloud.com
Requires-Python: >=3.6.1,<4.0.0
Classifier: License :: OSI Approved :: BSD License
Classifier: Programming Language :: Python :: 3
Classifier: Programming Language :: Python :: 3.7
Classifier: Programming Language :: Python :: 3.8
Requires-Dist: pandas (>=1.0.0,<2.0.0)
Requires-Dist: pdfkit (>=0.6.1,<0.7.0)
Requires-Dist: wkhtmltopdf (>=0.2,<0.3)
